[
  {
    "id": 9223372036854346000,
    "category": {
      "id": 0,
      "name": "string"
    },
    "name": "Virtualcat",
    "photoUrls": [
      "string"
    ],
    "tags": [
      {
        "id": 0,
        "name": "string"
      }
    ],
    "status": "sold"
  },
  {
    "id": 9223372036854764000,
    "category": {
      "id": -88990991,
      "name": "ea commodo dolor irure"
    },
    "name": "doggie",
    "photoUrls": [
      "Lorem culpa tempor laborum elit",
      "veniam adipisicing aliqua"
    ],
    "tags": [
      {
        "id": 54287335,
        "name": "enim nisi commodo"
      },
      {
        "id": -43453937,
        "name": "laborum"
      }
    ],
    "status": "sold"
  },
  {
    "id": 37930519,
    "category": {
      "id": -20083820,
      "name": "est"
    },
    "name": "doggie",
    "photoUrls": [
      "consectetur",
      "proident sint"
    ],
    "tags": [
      {
        "id": -50305895,
        "name": "occaecat labore"
      },
      {
        "id": -90748378,
        "name": "Duis irure"
      }
    ],
    "status": "sold"
  },
  {
    "id": 922337203685477600,
    "name": "chappi dog 78",
    "photoUrls": [
      "./dog.png"
    ],
    "tags": [],
    "status": "sold"
  },
  {
    "id": 3893738347,
    "category": {
      "id": 3368122887,
      "name": "dog"
    },
    "name": "hello kity",
    "photoUrls": [
      "http://foo.bar.com/1",
      "http://foo.bar.com/2"
    ],
    "tags": [
      {
        "id": 3776241980,
        "name": "blank"
      }
    ],
    "status": "sold"
  },
  {
    "id": 2090656926,
    "category": {
      "id": 3568170590,
      "name": "dog"
    },
    "name": "hello kity",
    "photoUrls": [
      "http://foo.bar.com/1",
      "http://foo.bar.com/2"
    ],
    "tags": [
      {
        "id": 1394796145,
        "name": "blank"
      }
    ],
    "status": "sold"
  },
  {
    "id": 3473852319,
    "category": {
      "id": 4185950579,
      "name": "dog"
    },
    "name": "hello kity",
    "photoUrls": [
      "http://foo.bar.com/1",
      "http://foo.bar.com/2"
    ],
    "tags": [
      {
        "id": 3996873858,
        "name": "blank"
      }
    ],
    "status": "sold"
  },
  {
    "id": 1930473178,
    "category": {
      "id": 3349329014,
      "name": "dog"
    },
    "name": "hello kity",
    "photoUrls": [
      "http://foo.bar.com/1",
      "http://foo.bar.com/2"
    ],
    "tags": [
      {
        "id": 3050991733,
        "name": "blank"
      }
    ],
    "status": "sold"
  },
  {
    "id": 4214032960,
    "category": {
      "id": 2685551619,
      "name": "dog"
    },
    "name": "hello kity",
    "photoUrls": [
      "http://foo.bar.com/1",
      "http://foo.bar.com/2"
    ],
    "tags": [
      {
        "id": 684606313,
        "name": "blank"
      }
    ],
    "status": "sold"
  },
  {
    "id": 837,
    "category": {
      "id": 91,
      "name": "focus"
    },
    "name": "Dr. Tina Chapman",
    "photoUrls": [],
    "tags": [
      {
        "id": 49,
        "name": "catch"
      }
    ],
    "status": "sold"
  }
]